uniton/__init__.py
uniton/__main__.py
uniton/core.dll
uniton/csobject.py
uniton/csutil.py
uniton/examples.py
uniton/namespace.py
uniton/protocol.py
uniton/render.py
uniton/scene.py
uniton/timing.py
uniton/unityengine.py
uniton/unityproc.py
uniton/util/__init__.py
uniton/util/appdirs.py
uniton-0.3.6.dist-info/METADATA
uniton-0.3.6.dist-info/WHEEL
uniton-0.3.6.dist-info/top_level.txt
uniton-0.3.6.dist-info/RECORD
