Metadata-Version: 2.1
Name: uniton
Version: 0.3.6
Summary: Control Unity from Python
Home-page: https://github.com/rmst/uniton
Author: Simon Ramstedt
Author-email: simonramstedt@gmail.com
License: UNKNOWN
Platform: UNKNOWN
